.gitignore
setup.py
payyans/__init__.py
payyans/core.py
payyans.egg-info/PKG-INFO
payyans.egg-info/SOURCES.txt
payyans.egg-info/dependency_links.txt
payyans.egg-info/not-zip-safe
payyans.egg-info/requires.txt
payyans.egg-info/top_level.txt
payyans/maps/ambili.map
payyans/maps/charaka.map
payyans/maps/indulekha.map
payyans/maps/karthika.map
payyans/maps/manorama.map
payyans/maps/matweb.map
payyans/maps/revathi.map
payyans/maps/template.map
payyans/maps/uma.map
payyans/maps/valluvar.map
payyans/templates/payyans.html