Metadata-Version: 1.0
Name: payyans
Version: 0.2
Summary: ASCII to Unicode converter
Home-page: http://silpa.org.in/payyans
Author: Santhosh Thottingal
Author-email: santhosh.thottingal@gmail.com
License: LGPL 3.0
Platform: UNKNOWN
